genetic_prompt_compiler/__init__.py
genetic_prompt_compiler/fitness/__init__.py
genetic_prompt_compiler/fitness/rule_based.py
genetic_prompt_compiler/mutate/__init__.py
genetic_prompt_compiler/mutate/rule_based.py
genetic_prompt_compiler/ranking/__init__.py
genetic_prompt_compiler/ranking/top_n.py
genetic_prompt_compiler-0.2.1.dist-info/LICENSE
genetic_prompt_compiler-0.2.1.dist-info/METADATA
genetic_prompt_compiler-0.2.1.dist-info/WHEEL
genetic_prompt_compiler-0.2.1.dist-info/RECORD
