Metadata-Version: 2.1
Name: genetic-prompt-compiler
Version: 0.2.1
Summary: 
Author: Antonin Deniau
Author-email: antonin.deniau@gmail.com
Requires-Python: >=3.11,<4.0
Classifier: Programming Language :: Python :: 3
Classifier: Programming Language :: Python :: 3.11
Classifier: Programming Language :: Python :: 3.12
Requires-Dist: tqdm (>=4.66.1,<5.0.0)
